defines.v
// RISC-V RV32I opcode and funct3 definitions for the simple testbench
`ifndef DEFINES_V
`define DEFINES_V

// Opcodes (7 bits)
`define OP_LOAD   7'b0000011
`define OP_STORE  7'b0100011
`define OP_BRANCH 7'b1100011
`define OP_IMM    7'b0010011
`define OP_OP     7'b0110011
`define OP_JAL    7'b1101111
`define OP_JALR   7'b1100111
`define OP_LUI    7'b0110111
`define OP_AUIPC  7'b0010111

// funct3 codes (3 bits)
// Branches
`define OP_BEQ  3'b000
`define OP_BNE  3'b001
`define OP_BLT  3'b100
`define OP_BGE  3'b101
`define OP_BLTU 3'b110
`define OP_BGEU 3'b111

// Loads
`define OP_LB  3'b000
`define OP_LH  3'b001
`define OP_LW  3'b010
`define OP_LBU 3'b100
`define OP_LHU 3'b101

`endif

alu.v
module alu #(
    parameter DATA_W =32,
    parameter SHAMT_W = 5,
    parameter OP =3
)(
    input wire [DATA_W-1:0] a,
    input wire [DATA_W-1:0] b,
    input wire [OP-1:0]     s,
    input wire              ext,
    output reg [DATA_W-1:0] y
);

    wire [SHAMT_W-1:0] shamt = b[SHAMT_W-1:0]; //SHAMT= Shift amount

    always @(*) begin
        case (s)
        3'b000: y= ext ? (a-b) : (a+b); // ADD bolon SUB iig ext ga set bolson ued shiideh heseg
        3'b111: y= a & b;               // AND
        3'b110: y= a | b;               // OR
        3'b100: y= a ^ b;               // XOR
        3'b001: y= a << shamt;          // SLL
        3'b101:  begin
            if (ext)
                y = $signed(a) >>> shamt; //arithmetic shift right
            else
                y = a >> shamt;         //logical shift right
        end
        default: y=0;
     endcase
    end
endmodule

reg.v
module rfile #(
    parameter REG_W = -1,
    parameter REG_S = -1,
    parameter DATA_W = -1
)(
    input wire  clk,
    input wire [REG_W-1:0] a1,a2,a3,
    output wire [DATA_W-1:0] rd1,rd2,
    input wire [DATA_W-1:0] wd,
    input wire              we
);
    reg [DATA_W-1:0] rf [0:REG_S-1];

    //debug processing just easier debugging 
    wire [DATA_W-1:0] x1;
    assign x1 = rf[1];
    //------

    // x0は常に０，それ以外はレジスタ値11‐17に更新RISC-V的に正しいらしい。
    assign rd1 = (a1 == 0) ? {DATA_W{1'b0}} : rf[a1];
    assign rd2 = (a2 == 0) ? {DATA_W{1'b0}} : rf[a2];

    always @(posedge clk) begin
        // x0 に書き込まん
        if (we && (a3 != 0)) begin
            rf[a3] <= wd;
        end
    end
endmodule

rv32i.v

`include "defines.v"

module rv32i #(
    //  --------------------------------------------------------------------
    //  parameter declare
    //  --------------------------------------------------------------------
    parameter   MEMORY_S    =   2**8,
    parameter   OPCODE_W    =   7,
    parameter   SHAMT_W     =   5,
    parameter   OP          =   3,
    parameter   PC_W        =   8,
    parameter   REG_W       =   5,
    parameter   DATA_W      =   32,
    parameter   REG_S       =   32,
    parameter   FUNCT3      =   3,
    parameter   FUNCT7      =   7,
    parameter   IMM         =   32,
    parameter   BYTE        =   8,
    parameter   HALF        =   2*BYTE,
    parameter   WORD        =   4*BYTE,
    parameter   STORE_M     =   2
)(
    // input wire
    input wire                  clk,
    input wire                  n_rst,

    // input from instruction mem
    input wire  [DATA_W-1:0]    instruction,
    // output to instruction mem
    output wire [PC_W-1:0]      pc,

    // input from data mem
    input wire  [DATA_W-1:0]    d_in,

    // output to data mem
    output wire                 wr_en,
    output wire [STORE_M-1:0]   mode,
    output wire [PC_W-1:0]      wr_addr,
    output wire [PC_W-1:0]      rd_addr,
    output wire [DATA_W-1:0]    d_out
);

    reg [PC_W - 1:0]        pc_reg;
    reg [DATA_W - 1:0]      inst;
    wire                    r_we;
    wire [PC_W-1:0]         pc_next;

    assign pc    = pc_reg;

    //  --------------------------------------------------------------------
    //  Fetch STAGE
    //  --------------------------------------------------------------------

    always @(posedge clk or negedge n_rst) begin
        if (!n_rst) begin
            pc_reg <= 0;
        end else begin
            pc_reg <= pc_next;
        end
    end

    always @(posedge clk or negedge n_rst) begin
        if (!n_rst) begin
            inst <= 0;
        end else begin
            inst <= instruction;
        end
    end


    //  --------------------------------------------------------------------
    //  Decode STAGE
    //  --------------------------------------------------------------------

    wire    [REG_W-1:0]     rs1,rs2,rd;
    wire    [DATA_W-1:0]    rdata1,rdata2;
    wire                    aluop;
    wire    [OPCODE_W-1:0]  opcode;
    wire    [FUNCT3-1:0]    funct3;
    wire    [FUNCT7-1:0]    funct7;
    wire    [DATA_W-1:0]    imm_i, imm_s, imm_b, imm_j, imm_u;
    wire    [DATA_W-1:0]    imm_sel;

    reg     [REG_W-1:0]     rd_E;
    reg     [DATA_W-1:0]    rdata_E1,rdata_E2;
    reg                     aluop_E;
    reg     [OP-1:0]        funct3_E;
    reg     [IMM-1:0]       imm_E;
    reg     [OPCODE_W-1:0]  opcode_E;
    reg     [PC_W-1:0]      pc_E;

    assign funct7   = inst[31:25];
    assign rs2      = inst[24:20];
    assign rs1      = inst[19:15];
    assign funct3   = inst[14:12];
    assign rd       = inst[11:7];
    assign opcode   = inst[6:0];
    assign aluop    = inst[30];

    // Immediate decode (sign-extended to DATA_W)
    assign imm_i = {{20{inst[31]}}, inst[31:20]};
    assign imm_s = {{20{inst[31]}}, inst[31:25], inst[11:7]};
    assign imm_b = {{19{inst[31]}}, inst[31], inst[7], inst[30:25], inst[11:8], 1'b0};
    assign imm_j = {{11{inst[31]}}, inst[31], inst[19:12], inst[20], inst[30:21], 1'b0};
    assign imm_u = {inst[31:12], 12'b0};

    assign imm_sel = (opcode == `OP_LOAD   || opcode == `OP_IMM   || opcode == `OP_JALR) ? imm_i :
                     (opcode == `OP_STORE)   ? imm_s :
                     (opcode == `OP_BRANCH)  ? imm_b :
                     (opcode == `OP_JAL)     ? imm_j :
                     (opcode == `OP_LUI || opcode == `OP_AUIPC) ? imm_u :
                     imm_i;
    
    // Early PC control (Decode stage) - detect jumps immediately
    wire                    is_jal_D;
    wire                    is_jalr_D;
    wire    [PC_W-1:0]      jal_target_D;
    wire    [PC_W-1:0]      jalr_target_D;
    wire    [DATA_W-1:0]    jal_sum_D;
    wire    [DATA_W-1:0]    jalr_sum_D;
    
    assign is_jal_D       = (opcode == `OP_JAL);
    assign is_jalr_D      = (opcode == `OP_JALR);
    assign jal_sum_D      = pc_reg + imm_sel;
    assign jalr_sum_D     = rdata1 + imm_sel;
    assign jal_target_D   = jal_sum_D[PC_W-1:0];
    assign jalr_target_D  = jalr_sum_D[PC_W-1:0];
       
    rfile #(
        .REG_W(REG_W),
        .DATA_W(DATA_W),
        .REG_S(REG_S)
    )rfile(
        .clk(clk),
        .a1(rs1),       // read address 1
        .a2(rs2),       // read address 2
        .a3(rd_W),      // write address
        .rd1(rdata1),   // read data 1
        .rd2(rdata2),   // read data 2
        .wd(wd),        // write data
        .we(r_we)       // write enable
    );

    always @(posedge clk) begin
        rdata_E1    <= rdata1;
        rdata_E2    <= rdata2;
        rd_E        <= rd;
        funct3_E    <= funct3;
        aluop_E     <= aluop;
        opcode_E    <= opcode;
        imm_E       <= imm_sel;
        pc_E        <= pc_reg;
    end

    //  --------------------------------------------------------------------
    //  Execute STAGE
    //  --------------------------------------------------------------------

    reg     [DATA_W-1:0]    alu_res_M;
    reg     [REG_W-1:0]     rd_M;
    reg     [FUNCT3-1:0]    funct3_M;
    reg     [DATA_W-1:0]    rdata_M1,rdata_M2;
    reg     [OPCODE_W-1:0]  opcode_M;
    reg     [PC_W-1:0]      pc_M;
    wire    [DATA_W-1:0]    alu_res;
    wire    [DATA_W-1:0]    in_a, in_b;
    wire    [FUNCT3-1:0]    s;
    wire                    branch_taken_E;
    wire    [PC_W-1:0]      pc_plus4;
    wire    [PC_W-1:0]      branch_target;
    wire    [PC_W-1:0]      jal_target;
    wire    [PC_W-1:0]      jalr_target;
    wire                    use_imm_E;
    reg     [PC_W-1:0]      pc_next_r;
    wire    [DATA_W-1:0]    branch_sum;
    wire    [DATA_W-1:0]    jal_sum;
    wire    [DATA_W-1:0]    jalr_sum;

    assign s        = (opcode_E == `OP_OP || opcode_E == `OP_IMM) ? funct3_E : 0;
    assign use_imm_E= (opcode_E == `OP_LOAD)  || (opcode_E == `OP_STORE) ||
                      (opcode_E == `OP_IMM)   || (opcode_E == `OP_JAL)   ||
                      (opcode_E == `OP_JALR)  || (opcode_E == `OP_LUI)   ||
                      (opcode_E == `OP_AUIPC);
    assign in_a     = (opcode_E == `OP_AUIPC) ? pc_E : (opcode_E == `OP_LUI ? {DATA_W{1'b0}} : rdata_E1);
    assign in_b     = use_imm_E ? imm_E : rdata_E2;

    assign branch_taken_E = (opcode_E == `OP_BRANCH) && (funct3_E == `OP_BEQ) && (rdata_E1 == rdata_E2);
    assign pc_plus4       = pc_reg + 8'd4;
    assign branch_sum     = pc_E + imm_E;
    assign branch_target  = branch_sum[7:0];

    // PC update: prioritize Decode-stage jumps (JAL/JALR) over Execute-stage branches
    always @(*) begin
        pc_next_r = pc_plus4;
        if (branch_taken_E)  pc_next_r = branch_target;
        if (is_jal_D)        pc_next_r = jal_target_D;
        if (is_jalr_D)       pc_next_r = jalr_target_D;
    end

    assign pc_next = pc_next_r;

    alu #(
        .DATA_W(DATA_W),
        .SHAMT_W(SHAMT_W),
        .OP(OP)
    )alu(
        .a(in_a),
        .b(in_b),
        .s(s), // need 0
        .ext(aluop_E),
        .y(alu_res)
    );

    always @(posedge clk)begin
        alu_res_M   <= alu_res;
        rd_M        <= rd_E;
        funct3_M    <= funct3_E;
        opcode_M    <= opcode_E;
        rdata_M1    <= rdata_E1;
        rdata_M2    <= rdata_E2;
        pc_M        <= pc_E;
    end

    //  --------------------------------------------------------------------
    //  Memory STAGE
    //  --------------------------------------------------------------------

    wire    [DATA_W-1:0]    rd_data;

    reg     [OPCODE_W-1:0]  opcode_W;
    reg     [DATA_W-1:0]    rd_data_W;
    reg     [DATA_W-1:0]    alu_res_W;
    reg     [REG_W-1:0]     rd_W;
    reg     [PC_W-1:0]      pc_W;

    assign rd_addr  = alu_res_M;
    assign rd_data  = rd_data_sel(funct3_M,d_in);

    function [DATA_W-1:0] rd_data_sel(
        input [FUNCT3-1:0] funct,
        input [DATA_W-1:0] data
    );
        case(funct)
            3'b000 : rd_data_sel = (data[7]) ? {24'hFFFFFF,data[7:0]}:{24'h0,data[7:0]};
            3'b001 : rd_data_sel = (data[15]) ? {16'hFFFF,data[15:0]}:{16'h0,data[15:0]};
            3'b010 : rd_data_sel = data;
            3'b100 : rd_data_sel = {24'h0,data[7:0]};
            3'b101 : rd_data_sel = {16'h0,data[15:0]};
            default: rd_data_sel = 32'h0;
        endcase
    endfunction


    always @(posedge clk) begin
        opcode_W    <= opcode_M;
        rd_data_W   <= rd_data;
        rd_W        <= rd_M;
        alu_res_W   <= alu_res_M;
        pc_W        <= pc_M;
    end

    //  --------------------------------------------------------------------
    //  Write Back STAGE
    //  --------------------------------------------------------------------

    wire [DATA_W-1:0]   wd;
    wire [DATA_W-1:0]   jal_link;

    assign jal_link  = pc_W + 32'd4;
    assign wd        = (opcode_W == `OP_LOAD)                         ? rd_data_W :
                       (opcode_W == `OP_OP   || opcode_W == `OP_IMM ||
                        opcode_W == `OP_AUIPC || opcode_W == `OP_LUI) ? alu_res_W :
                       (opcode_W == `OP_JAL  || opcode_W == `OP_JALR) ? jal_link :
                       rd_data_W;

    assign r_we     = (opcode_W == `OP_LOAD)  || (opcode_W == `OP_OP)   ||
                      (opcode_W == `OP_IMM)   || (opcode_W == `OP_JAL)  ||
                      (opcode_W == `OP_JALR)  || (opcode_W == `OP_LUI)  ||
                      (opcode_W == `OP_AUIPC);
    
    // Output assignments
    assign wr_en    = (opcode_M == `OP_STORE);
    assign mode     = funct3_M[1:0];
    assign wr_addr  = alu_res_M;
    assign d_out    = rdata_M2;
endmodule

d_mem.v
module d_mem #(
    parameter   M_WIDTH     =   -1,
    parameter   M_STACK     =   -1,
    parameter   DATA_W      =   -1,
    parameter   PC_WIDTH    =   -1,
    parameter   STORE_M     =   -1,
    parameter   ADDR_WIDTH  =   -1,
    parameter   DATA_INIT_FILE = "data_mem.dat"
)(
    input wire                  clk,
    input wire                  n_rst,
    input wire                  wr_en,
    input wire  [PC_WIDTH-1:0]  rd_addr,
    input wire  [PC_WIDTH-1:0]  wr_addr,
    input wire  [STORE_M-1:0]   mode,
    input wire  [DATA_W-1:0]    d_in,
    output wire [DATA_W-1:0]    d_out
);
    localparam ST_B = 2'b00;
    localparam ST_H = 2'b01;
    localparam ST_W = 2'b10;

    reg [ADDR_WIDTH-1:0] ram [0:M_STACK-1];
    initial $readmemb(DATA_INIT_FILE,ram);

    // Little-endian: lowest address is least-significant byte(Hamgiin tom dugaartai addressaasaa oruulj ehelne gesen ug)
    assign d_out    = {ram[rd_addr+3],ram[rd_addr+2],ram[rd_addr+1],ram[rd_addr]};

    always @(posedge clk) begin
        if (wr_en) begin
            if (mode == ST_B) begin
                ram[wr_addr] <= d_in[ADDR_WIDTH-1:0];
            end else if (mode == ST_H) begin
                {ram[wr_addr+1],ram[wr_addr]} <= {d_in[(ADDR_WIDTH*2)-1:ADDR_WIDTH],d_in[ADDR_WIDTH-1:0]};
            end else if (mode == ST_W) begin
                {ram[wr_addr+3],ram[wr_addr+2],ram[wr_addr+1],ram[wr_addr]} <= d_in;
            end else begin
                {ram[wr_addr],ram[wr_addr+1],ram[wr_addr+2],ram[wr_addr+3]} <= 32'hzzzzzzzz;
            end
        end
    end

endmodule

i_mem.v
module i_mem #(
    parameter   M_WIDTH     =   -1,
    parameter   M_STACK     =   -1,
    parameter   DATA_W      =   -1,
    parameter   PC_WIDTH    =   -1,
    parameter   ADDR_WIDTH  =   -1,
    parameter   MEM_INIT_FILE = "mem.bin"
)(
    input wire                  clk,
    input wire                  n_rst,
    input wire  [PC_WIDTH-1:0]  rd_addr,
    output wire [DATA_W-1:0]    d_out
);

    reg     [ADDR_WIDTH-1:0] ram [0:M_STACK-1];

    initial $readmemb(MEM_INIT_FILE,ram);

    // Little-endian: lowest address is least-significant byte
    assign d_out    = {ram[rd_addr+3],ram[rd_addr+2],ram[rd_addr+1],ram[rd_addr]};

endmodule

tb_cpu1_stepA.v
`timescale 1ns/1ps

module tb_cpu1_stepA;

	// clock/reset
	reg clk = 0;
	reg rst_n = 0;
	always #5 clk = ~clk;
	initial begin
		rst_n = 0;
		repeat (5) @(posedge clk);
		rst_n = 1;
	end

	// wires to DUT
	wire [31:0] instr;
	wire [7:0]  pc;
	wire [31:0] dmem_rdata;
	wire [31:0] dmem_wdata;
	wire        dmem_we;
	wire [1:0]  dmem_mode;
	wire [7:0]  dmem_waddr;
	wire [7:0]  dmem_raddr;

	reg [31:0] result;

	// instruction memory (Step A image)
	i_mem #(
		.M_STACK(256), .DATA_W(32), .PC_WIDTH(8), .ADDR_WIDTH(8),
		.MEM_INIT_FILE("mem_cpu1_stepA.bin")
	) u_imem (
		.clk(clk),
		.n_rst(rst_n),
		.rd_addr(pc),
		.d_out(instr)
	);

	// data memory (Step A image)
	d_mem #(
		.M_STACK(256), .DATA_W(32), .PC_WIDTH(8), .ADDR_WIDTH(8), .STORE_M(2),
		.DATA_INIT_FILE("data_cpu1_stepA.dat")
	) u_dmem (
		.clk(clk),
		.n_rst(rst_n),
		.wr_en(dmem_we),
		.rd_addr(dmem_raddr),
		.wr_addr(dmem_waddr),
		.mode(dmem_mode),
		.d_in(dmem_wdata),
		.d_out(dmem_rdata)
	);

	// DUT
	rv32i u_cpu (
		.clk(clk),
		.n_rst(rst_n),
		.instruction(instr),
		.pc(pc),
		.d_in(dmem_rdata),
		.wr_en(dmem_we),
		.mode(dmem_mode),
		.wr_addr(dmem_waddr),
		.rd_addr(dmem_raddr),
		.d_out(dmem_wdata)
	);

	// test sequence
	initial begin
		$dumpfile("stepA.vcd");
		$dumpvars(0, tb_cpu1_stepA);

		// run for a bounded number of cycles
		repeat (200) @(posedge clk);

		// observe mem[8] as 32-bit little endian
		result = {u_dmem.ram[11], u_dmem.ram[10], u_dmem.ram[9], u_dmem.ram[8]};

		if (result == 32'h1) begin
			$display("TEST RESULT: PASS (mem[8]=1)");
		end else begin
			$display("TEST RESULT: FAIL (mem[8]=%h)", result);
		end

		$finish;
	end

endmodule

stepA.vcd
$date
	Tue Dec 23 15:35:05 2025
$end
$version
	Icarus Verilog
$end
$timescale
	1ps
$end
$scope module tb_cpu1_stepA $end
$var wire 8 ! pc [7:0] $end
$var wire 32 " instr [31:0] $end
$var wire 1 # dmem_we $end
$var wire 32 $ dmem_wdata [31:0] $end
$var wire 8 % dmem_waddr [7:0] $end
$var wire 32 & dmem_rdata [31:0] $end
$var wire 8 ' dmem_raddr [7:0] $end
$var wire 2 ( dmem_mode [1:0] $end
$var reg 1 ) clk $end
$var reg 32 * result [31:0] $end
$var reg 1 + rst_n $end
$scope module u_cpu $end
$var wire 1 , branch_taken_E $end
$var wire 1 ) clk $end
$var wire 32 - d_out [31:0] $end
$var wire 1 + n_rst $end
$var wire 8 . pc [7:0] $end
$var wire 8 / pc_next [7:0] $end
$var wire 1 0 r_we $end
$var wire 1 1 use_imm_E $end
$var wire 1 # wr_en $end
$var wire 8 2 wr_addr [7:0] $end
$var wire 32 3 wd [31:0] $end
$var wire 3 4 s [2:0] $end
$var wire 5 5 rs2 [4:0] $end
$var wire 5 6 rs1 [4:0] $end
$var wire 32 7 rdata2 [31:0] $end
$var wire 32 8 rdata1 [31:0] $end
$var wire 32 9 rd_data [31:0] $end
$var wire 8 : rd_addr [7:0] $end
$var wire 5 ; rd [4:0] $end
$var wire 8 < pc_plus4 [7:0] $end
$var wire 7 = opcode [6:0] $end
$var wire 2 > mode [1:0] $end
$var wire 8 ? jalr_target_D [7:0] $end
$var wire 32 @ jalr_sum_D [31:0] $end
$var wire 8 A jal_target_D [7:0] $end
$var wire 32 B jal_sum_D [31:0] $end
$var wire 32 C jal_link [31:0] $end
$var wire 1 D is_jalr_D $end
$var wire 1 E is_jal_D $end
$var wire 32 F instruction [31:0] $end
$var wire 32 G in_b [31:0] $end
$var wire 32 H in_a [31:0] $end
$var wire 32 I imm_u [31:0] $end
$var wire 32 J imm_sel [31:0] $end
$var wire 32 K imm_s [31:0] $end
$var wire 32 L imm_j [31:0] $end
$var wire 32 M imm_i [31:0] $end
$var wire 32 N imm_b [31:0] $end
$var wire 7 O funct7 [6:0] $end
$var wire 3 P funct3 [2:0] $end
$var wire 32 Q d_in [31:0] $end
$var wire 8 R branch_target [7:0] $end
$var wire 32 S branch_sum [31:0] $end
$var wire 1 T aluop $end
$var wire 32 U alu_res [31:0] $end
$var parameter 32 V BYTE $end
$var parameter 32 W DATA_W $end
$var parameter 32 X FUNCT3 $end
$var parameter 32 Y FUNCT7 $end
$var parameter 64 Z HALF $end
$var parameter 32 [ IMM $end
$var parameter 32 \ MEMORY_S $end
$var parameter 32 ] OP $end
$var parameter 32 ^ OPCODE_W $end
$var parameter 32 _ PC_W $end
$var parameter 32 ` REG_S $end
$var parameter 32 a REG_W $end
$var parameter 32 b SHAMT_W $end
$var parameter 32 c STORE_M $end
$var parameter 64 d WORD $end
$var reg 32 e alu_res_M [31:0] $end
$var reg 32 f alu_res_W [31:0] $end
$var reg 1 g aluop_E $end
$var reg 3 h funct3_E [2:0] $end
$var reg 3 i funct3_M [2:0] $end
$var reg 32 j imm_E [31:0] $end
$var reg 32 k inst [31:0] $end
$var reg 7 l opcode_E [6:0] $end
$var reg 7 m opcode_M [6:0] $end
$var reg 7 n opcode_W [6:0] $end
$var reg 8 o pc_E [7:0] $end
$var reg 8 p pc_M [7:0] $end
$var reg 8 q pc_W [7:0] $end
$var reg 8 r pc_next_r [7:0] $end
$var reg 8 s pc_reg [7:0] $end
$var reg 5 t rd_E [4:0] $end
$var reg 5 u rd_M [4:0] $end
$var reg 5 v rd_W [4:0] $end
$var reg 32 w rd_data_W [31:0] $end
$var reg 32 x rdata_E1 [31:0] $end
$var reg 32 y rdata_E2 [31:0] $end
$var reg 32 z rdata_M1 [31:0] $end
$var reg 32 { rdata_M2 [31:0] $end
$scope function rd_data_sel $end
$var reg 32 | data [31:0] $end
$var reg 3 } funct [2:0] $end
$upscope $end
$scope module alu $end
$var wire 32 ~ a [31:0] $end
$var wire 32 !" b [31:0] $end
$var wire 1 g ext $end
$var wire 3 "" s [2:0] $end
$var wire 5 #" shamt [4:0] $end
$var parameter 32 $" DATA_W $end
$var parameter 32 %" OP $end
$var parameter 32 &" SHAMT_W $end
$var reg 32 '" y [31:0] $end
$upscope $end
$scope module rfile $end
$var wire 5 (" a1 [4:0] $end
$var wire 5 )" a2 [4:0] $end
$var wire 5 *" a3 [4:0] $end
$var wire 1 ) clk $end
$var wire 32 +" wd [31:0] $end
$var wire 1 0 we $end
$var wire 32 ," x1 [31:0] $end
$var wire 32 -" rd2 [31:0] $end
$var wire 32 ." rd1 [31:0] $end
$var parameter 32 /" DATA_W $end
$var parameter 32 0" REG_S $end
$var parameter 32 1" REG_W $end
$upscope $end
$upscope $end
$scope module u_dmem $end
$var wire 1 ) clk $end
$var wire 32 2" d_in [31:0] $end
$var wire 2 3" mode [1:0] $end
$var wire 1 + n_rst $end
$var wire 8 4" rd_addr [7:0] $end
$var wire 8 5" wr_addr [7:0] $end
$var wire 1 # wr_en $end
$var wire 32 6" d_out [31:0] $end
$var parameter 32 7" ADDR_WIDTH $end
$var parameter 152 8" DATA_INIT_FILE $end
$var parameter 32 9" DATA_W $end
$var parameter 32 :" M_STACK $end
$var parameter 32 ;" M_WIDTH $end
$var parameter 32 <" PC_WIDTH $end
$var parameter 32 =" STORE_M $end
$var parameter 2 >" ST_B $end
$var parameter 2 ?" ST_H $end
$var parameter 2 @" ST_W $end
$upscope $end
$scope module u_imem $end
$var wire 1 ) clk $end
$var wire 1 + n_rst $end
$var wire 8 A" rd_addr [7:0] $end
$var wire 32 B" d_out [31:0] $end
$var parameter 32 C" ADDR_WIDTH $end
$var parameter 32 D" DATA_W $end
$var parameter 144 E" MEM_INIT_FILE $end
$var parameter 32 F" M_STACK $end
$var parameter 32 G" M_WIDTH $end
$var parameter 32 H" PC_WIDTH $end
$upscope $end
$upscope $end
$enddefinitions $end
$comment Show the parameter values. $end
$dumpall
b1000 H"
b11111111111111111111111111111111 G"
b100000000 F"
b11011010110010101101101010111110110001101110000011101010011000101011111011100110111010001100101011100000100000100101110011000100110100101101110 E"
b100000 D"
b1000 C"
b10 @"
b1 ?"
b0 >"
b10 ="
b1000 <"
b11111111111111111111111111111111 ;"
b100000000 :"
b100000 9"
b1100100011000010111010001100001010111110110001101110000011101010011000101011111011100110111010001100101011100000100000100101110011001000110000101110100 8"
b1000 7"
b101 1"
b100000 0"
b100000 /"
b101 &"
b11 %"
b100000 $"
b100000 d
b10 c
b101 b
b101 a
b100000 `
b1000 _
b111 ^
b11 ]
b100000000 \
b100000 [
b10000 Z
b111 Y
b11 X
b100000 W
b1000 V
$end
#0
$dumpvars
bx B"
bx A"
bx 6"
bx 5"
bx 4"
bx 3"
bx 2"
bx ."
bx -"
bx ,"
bx +"
bx *"
bx )"
bx ("
bx '"
bx #"
bx ""
bx !"
bx ~
bx }
bx |
bx {
bx z
bx y
bx x
bx w
bx v
bx u
bx t
bx s
bx r
bx q
bx p
bx o
bx n
bx m
bx l
bx k
bx j
bx i
bx h
xg
bx f
bx e
bx U
xT
bx S
bx R
bx Q
bx P
bx O
bx0 N
bx M
bx0 L
bx K
bx J
bx000000000000 I
bx H
bx G
bx F
xE
xD
bx C
bx B
bx A
bx @
bx ?
bx >
bx =
bx <
bx ;
bx :
b0 9
bx 8
bx 7
bx 6
bx 5
bx 4
bx 3
bx 2
x1
x0
bx /
bx .
bx -
x,
0+
bx *
0)
bx (
bx '
bx &
bx %
bx $
x#
bx "
bx !
$end
#5000
b0 ?
b0 A
b0 7
b0 -"
b0 @
b0 8
b0 ."
b0 B
b0 J
b100 /
b100 r
b0 O
b0 5
b0 )"
b0 6
b0 ("
b0 P
b0 ;
0E
0D
b0 =
0T
b0 M
b0 K
b0 N
b0 L
b0 I
b0 w
b100 <
b10000010000011 "
b10000010000011 F
b10000010000011 B"
b0 !
b0 .
b0 A"
b0 s
b0 k
1)
#10000
0)
#15000
01
b0 U
b0 '"
0,
b0 #"
b0 R
b0 H
b0 ~
b0 4
b0 ""
b0 G
b0 !"
b0 S
b0 o
b0 j
b0 l
0g
b0 h
b0 t
b0 y
b0 x
1)
#20000
0)
#25000
b1000100 9
b10001001000100011001101000100 |
b0 }
b0 (
b0 >
b0 3"
b10001001000100011001101000100 &
b10001001000100011001101000100 Q
b10001001000100011001101000100 6"
b0 '
b0 :
b0 4"
b0 %
b0 2
b0 5"
b0 p
b0 $
b0 -
b0 2"
b0 {
b0 z
0#
b0 m
b0 i
b0 u
b0 e
1)
#30000
0)
#35000
00
b1000100 3
b1000100 +"
b100 C
b0 q
b0 f
b0 v
b0 *"
b1000100 w
b0 n
1)
#40000
0)
#45000
1+
1)
#50000
0)
#55000
b10 P
b1 ;
b11 =
b1 K
b100000000000 N
b10000000000000 L
b10000000000000 I
b100 A
b1000 /
b1000 r
b10000010000011 k
b100 B
b1000 <
b100000010001000100011 "
b100000010001000100011 F
b100000010001000100011 B"
b100 !
b100 .
b100 A"
b100 s
1)
#60000
0)
#65000
11
b100 ?
bx 7
bx -"
b100 @
b100 J
b100 R
b1100 A
b1100 /
b1100 r
b1 5
b1 )"
b100 ;
b100011 =
b1 M
b100 K
b100 N
b10100000000000 L
b100000010000000000000 I
b100 S
b100 o
b11 l
b10 h
b1 t
b1100 B
b1100 <
b10000000010000100000011 "
b10000000010000100000011 F
b10000000010000100000011 B"
b1000 !
b1000 .
b1000 A"
b1000 s
b100000010001000100011 k
1)
#70000
0)
#75000
b100 ?
b100 @
b100 J
b100 U
b100 '"
b100 #"
b10001001000100011001101000100 9
b10 }
b10 (
b10 >
b10 3"
b100 G
b100 !"
b1100 R
b100 5
b100 )"
b10 ;
b11 =
b100 M
b10 K
b10 N
b10000000000100 L
b10000000010000000000000 I
b10000 A
b10000 /
b10000 r
b100 p
b11 m
b10 i
b1 u
b1000 o
b1100 S
b100 j
b100011 l
b100 t
bx y
b10000000010000100000011 k
b10000 B
b10000 <
b1000001000100001100011 "
b1000001000100001100011 F
b1000001000100001100011 B"
b1100 !
b1100 .
b1100 A"
b1100 s
1)
#80000
0)
#85000
10
bx ?
b0 9
b0 |
bx 8
bx ."
bx @
b10000 J
b10000 R
b0 &
b0 Q
b0 6"
b100 '
b100 :
b100 4"
b100 %
b100 2
b100 5"
b10001001000100011001101000100 3
b10001001000100011001101000100 +"
b100000 A
b10100 /
b10100 r
b10 5
b10 )"
b1 6
b1 ("
b0 P
b10000 ;
b1100011 =
b10 M
b10000 K
b10000 N
b1000000000000010 L
b1000001000000000000000 I
b10000 S
b1100 o
b11 l
b10 t
b1000 p
bx $
bx -
bx 2"
bx {
1#
b100011 m
b100 u
b100 e
b1000 C
b100 q
b1 v
b1 *"
b10001001000100011001101000100 w
b11 n
b100000 B
b10100 <
b110010011 "
b110010011 F
b110010011 B"
b10000 !
b10000 .
b10000 A"
b10000 s
b1000001000100001100011 k
1)
#90000
0)
#95000
00
01
b0 J
b0 3
b0 +"
bx U
bx '"
bx #"
x,
bx H
bx ~
b0 ?
b0 7
b0 -"
bx G
bx !"
b100000 R
b0 @
b0 8
b0 ."
bx 9
bx |
b0 5
b0 )"
b0 6
b0 ("
b11 ;
b10011 =
b0 M
b11 K
b100000000010 N
b0 L
b0 I
b10100 A
b11000 /
b11000 r
b1100 C
b1000 q
b100 f
b100 v
b100 *"
b0 w
b100011 n
b1100 p
0#
b11 m
b10 u
b10000 o
b100000 S
b10000 j
b1100011 l
b0 h
b10000 t
bx x
b10001001000100011001101000100 ,"
bx &
bx Q
bx 6"
b110010011 k
b10100 B
b11000 <
b1100000010010000100011 "
b1100000010010000100011 F
b1100000010010000100011 B"
b10100 !
b10100 .
b10100 A"
b10100 s
1)
#100000
0)
#105000
10
11
b1000 ?
b0 U
b0 '"
b0 #"
b0 H
b0 ~
bx 7
bx -"
b1000 @
b1000 J
b10100 R
b0 G
b0 !"
0,
b0 }
b0 (
b0 >
b0 3"
bx '
bx :
bx 4"
bx %
bx 2
bx 5"
bx 3
bx +"
b100000 A
b11100 /
b11100 r
b11 5
b11 )"
b10 P
b1000 ;
b100011 =
b11 M
b1000 K
b1000 N
b10100000000010 L
b1100000010000000000000 I
b10100 o
b10100 S
b0 j
b10011 l
b11 t
b0 y
b0 x
b10000 p
bx z
b1100011 m
b0 i
b10000 u
bx e
b10000 C
b1100 q
b10 v
b10 *"
bx w
b11 n
b100000 B
b11100 <
b110000000000000001101111 "
b110000000000000001101111 F
b110000000000000001101111 B"
b11000 !
b11000 .
b11000 A"
b11000 s
b1100000010010000100011 k
1)
#110000
0)
#115000
00
11
b1100 ?
b1000 U
b1000 '"
b1100 @
b1100 J
b1000100 9
b10001001000100011001101000100 |
b1000 #"
b10001001000100011001101000100 &
b10001001000100011001101000100 Q
b10001001000100011001101000100 6"
b0 '
b0 :
b0 4"
b0 %
b0 2
b0 5"
b1000 G
b1000 !"
b100000 R
b0 4
b0 ""
b1100 5
b1100 )"
b0 P
b0 ;
1E
b1101111 =
b1100 M
b0 K
b0 N
b1100 L
b110000000000000000000000 I
b101000 A
b101000 /
b101000 r
b10100 C
b10000 q
bx f
b10000 v
b10000 *"
b1100011 n
b10100 p
b0 $
b0 -
b0 2"
b0 {
b0 z
b10011 m
b11 u
b0 e
b11000 o
b100000 S
b1000 j
b100011 l
b10 h
b1000 t
bx y
b110000000000000001101111 k
b101000 B
b100000 <
b100000000000110010011 "
b100000000000110010011 F
b100000000000110010011 B"
b11100 !
b11100 .
b11100 A"
b11100 s
1)
#120000
0)
